{"library":{"publisher":[{"@name":"Wiley Group","book":[{"author":"Stephen King","title":"The Green Mile","price":18.0},{"author":"J. D. Salinger","title":"The Catcher in the Rye","price":25.0},{"author":"Issac Asimov","title":"I, Robot","price":15.0}]},{"@name":"Time Publishing","book":[{"author":"Isaac Asimov","title":"Foundation Novels","price":30.0},{"author":"Oscar Wilde","title":"Pygmalion","price":10.0}]},{"@name":"Amazon","book":[{"author":"Frank Herbert","title":"Dune","price":25.0},{"author":"Frank Herbert","title":"Dune Messiah","price":12.0}]}]}}